{
  "name": "linkmjb-jenkins_dood",
  "version": "0.1.0",
  "author": "linkmjb",
  "summary": "Puppet module for installing and managing a Jenkins DooD deployment",
  "license": "Apache-2.0",
  "source": "https://github.com/LinkMJB/jenkins_dood",
  "dependencies": [
    {
      "name": "puppetlabs-stdlib",
      "version_requirement": ">= 6.3.0"
    },
    {
      "name": "puppetlabs-docker",
      "version_requirement": ">= 3.10.1"
    }
  ],
  "operatingsystem_support": [
    {
      "operatingsystem": "RedHat",
      "operatingsystemrelease": [
        "7.0"
      ]
    }
  ],
  "requirements": [
    {
      "name": "puppet",
      "version_requirement": ">= 4.10.0 < 7.0.0"
    }
  ],
  "pdk-version": "1.18.0",
  "template-url": "pdk-default#1.18.0",
  "template-ref": "tags/1.18.0-0-g095317c"
}
